nheri_simcenter/__init__.py
nheri_simcenter-0.9.45.dist-info/licenses/LICENSE
nheri_simcenter-0.9.45.dist-info/METADATA
nheri_simcenter-0.9.45.dist-info/WHEEL
nheri_simcenter-0.9.45.dist-info/top_level.txt
nheri_simcenter-0.9.45.dist-info/RECORD
