Metadata-Version: 2.4
Name: nheri_simcenter
Version: 0.9.45
Summary: NHERI SimCenter Python Dependencies
Home-page: http://nheri-simcenter.github.io/nheri_simcenter/
Author: Adam Zsarnóczay
Author-email: adamzs@stanford.edu
License: BSD License
Platform: any
Classifier: Programming Language :: Python
Classifier: Development Status :: 5 - Production/Stable
Classifier: Natural Language :: English
Classifier: Environment :: Console
Classifier: Framework :: Jupyter
Classifier: Intended Audience :: Education
Classifier: Intended Audience :: Science/Research
Classifier: License :: OSI Approved :: BSD License
Classifier: Natural Language :: English
Classifier: Operating System :: Microsoft :: Windows
Classifier: Operating System :: MacOS :: MacOS X
Classifier: Operating System :: Unix
Classifier: Programming Language :: Python :: 3.9
Classifier: Programming Language :: Python :: 3.10
Classifier: Programming Language :: Python :: 3.11
Classifier: Programming Language :: Python :: 3.12
Classifier: Topic :: Scientific/Engineering
License-File: LICENSE
Requires-Dist: numpy==1.26.4
Requires-Dist: scipy==1.12.0
Requires-Dist: pandas==2.2.3
Requires-Dist: pydantic==2.4
Requires-Dist: geopandas==0.14.4
Requires-Dist: momepy==0.6.0
Requires-Dist: jupyter
Requires-Dist: openpyxl
Requires-Dist: tables
Requires-Dist: openseespy
Requires-Dist: scikit-learn
Requires-Dist: plotly
Requires-Dist: colorlover
Requires-Dist: jpype1
Requires-Dist: tqdm
Requires-Dist: gpy==1.13.2
Requires-Dist: emukit
Requires-Dist: psutil
Requires-Dist: numpy-stl
Requires-Dist: pyredi
Requires-Dist: pelicun~=3.8.0
Requires-Dist: rasterio
Requires-Dist: ujson==5.9
Requires-Dist: xlrd
Requires-Dist: matplotlib==3.9.2
Requires-Dist: chardet
Requires-Dist: backtrace
Requires-Dist: welib
Requires-Dist: sympy
Requires-Dist: openquake.engine==3.17.1
Requires-Dist: h5py
Requires-Dist: rewet
Requires-Dist: pyvista[all]
Requires-Dist: tapipy
Requires-Dist: reverse_geocode
Requires-Dist: contextily
Requires-Dist: pandana
Requires-Dist: dill==0.3.9
Requires-Dist: pyogrio==0.10.0
Provides-Extra: testing
Requires-Dist: pytest; extra == "testing"
Dynamic: author
Dynamic: author-email
Dynamic: classifier
Dynamic: description
Dynamic: description-content-type
Dynamic: home-page
Dynamic: license
Dynamic: license-file
Dynamic: platform
Dynamic: provides-extra
Dynamic: requires-dist
Dynamic: summary
